HISTORY.md
LICENSE
MANIFEST.in
README.md
TODO.md
setup.py
setup_description.rst
test_pystache.py
tox.ini
pymstache/__init__.py
pymstache/common.py
pymstache/context.py
pymstache/defaults.py
pymstache/init.py
pymstache/loader.py
pymstache/locator.py
pymstache/parsed.py
pymstache/parser.py
pymstache/renderengine.py
pymstache/renderer.py
pymstache/specloader.py
pymstache/template_spec.py
pymstache.egg-info/PKG-INFO
pymstache.egg-info/SOURCES.txt
pymstache.egg-info/dependency_links.txt
pymstache.egg-info/entry_points.txt
pymstache.egg-info/requires.txt
pymstache.egg-info/top_level.txt
pymstache/commands/__init__.py
pymstache/commands/render.py
pymstache/commands/test.py
pymstache/tests/__init__.py
pymstache/tests/benchmark.py
pymstache/tests/common.py
pymstache/tests/doctesting.py
pymstache/tests/main.py
pymstache/tests/spectesting.py
pymstache/tests/test___init__.py
pymstache/tests/test_commands.py
pymstache/tests/test_context.py
pymstache/tests/test_defaults.py
pymstache/tests/test_examples.py
pymstache/tests/test_loader.py
pymstache/tests/test_locator.py
pymstache/tests/test_parser.py
pymstache/tests/test_pystache.py
pymstache/tests/test_renderengine.py
pymstache/tests/test_renderer.py
pymstache/tests/test_simple.py
pymstache/tests/test_specloader.py
pymstache/tests/data/__init__.py
pymstache/tests/data/ascii.mustache
pymstache/tests/data/duplicate.mustache
pymstache/tests/data/non_ascii.mustache
pymstache/tests/data/sample_view.mustache
pymstache/tests/data/say_hello.mustache
pymstache/tests/data/views.py
pymstache/tests/data/locator/__init__.py
pymstache/tests/data/locator/duplicate.mustache
pymstache/tests/data/locator/template.txt
pymstache/tests/examples/__init__.py
pymstache/tests/examples/comments.mustache
pymstache/tests/examples/comments.py
pymstache/tests/examples/complex.mustache
pymstache/tests/examples/complex.py
pymstache/tests/examples/delimiters.mustache
pymstache/tests/examples/delimiters.py
pymstache/tests/examples/double_section.mustache
pymstache/tests/examples/double_section.py
pymstache/tests/examples/escaped.mustache
pymstache/tests/examples/escaped.py
pymstache/tests/examples/inner_partial.mustache
